.gitignore
README.md
requirements.txt
setup.py
examples/__init__.py
examples/basic_example.py
typesense_orm/__init__.py
typesense_orm/api_caller.py
typesense_orm/base_model.py
typesense_orm/config.py
typesense_orm/exception_dict.py
typesense_orm/exceptions.py
typesense_orm/field.py
typesense_orm/higher_client.py
typesense_orm/logging.py
typesense_orm/lower_client.py
typesense_orm/schema.py
typesense_orm/search.py
typesense_orm/types.py
typesense_orm.egg-info/PKG-INFO
typesense_orm.egg-info/SOURCES.txt
typesense_orm.egg-info/dependency_links.txt
typesense_orm.egg-info/requires.txt
typesense_orm.egg-info/top_level.txt