Metadata-Version: 2.1
Name: typesense-orm
Version: 0.0.11
Summary: A typesense-server client using orm paradigm based on pydantic
Home-page: https://github.com/RedSnail/typesense_orm
Author: Oleg Demianchenko
Author-email: oleg.demianchenko@gmail.com
License: MIT
Platform: OS Independent
Requires-Python: >=3.8
